{
  "accentColor": "{{appsmith.theme.colors.primaryColor}}",
  "animateLoading": true,
  "autoFocus": false,
  "borderRadius": "{{appsmith.theme.borderRadius.appBorderRadius}}",
  "bottomRow": 15,
  "boxShadow": "none",
  "defaultText": "",
  "dynamicBindingPathList": [
    {
      "key": "accentColor"
    },
    {
      "key": "borderRadius"
    }
  ],
  "dynamicHeight": "FIXED",
  "iconAlign": "left",
  "inputType": "TEXT",
  "isDisabled": false,
  "isLoading": false,
  "isRequired": false,
  "isVisible": true,
  "key": "tk5fkkdjvp",
  "label": "Label",
  "labelAlignment": "left",
  "labelPosition": "Top",
  "labelStyle": "",
  "labelTextSize": "0.875rem",
  "labelWidth": 5,
  "leftColumn": 7,
  "maxDynamicHeight": 9000,
  "minDynamicHeight": 4,
  "minWidth": 450,
  "mobileBottomRow": 18,
  "mobileLeftColumn": 6,
  "mobileRightColumn": 26,
  "mobileTopRow": 11,
  "needsErrorInfo": false,
  "parentColumnSpace": 17.53125,
  "parentId": "0",
  "parentRowSpace": 10,
  "renderMode": "CANVAS",
  "resetOnSubmit": true,
  "responsiveBehavior": "fill",
  "rightColumn": 27,
  "showStepArrows": false,
  "topRow": 8,
  "type": "INPUT_WIDGET_V2",
  "version": 2,
  "widgetId": "00hlp8qnfw",
  "widgetName": "Input1"
}